elfragmentador/__init__.py
elfragmentador/cli.py
elfragmentador/config/__init__.py
elfragmentador/config/default_config.toml
elfragmentador/data/converter.py
elfragmentador/data/datamodules.py
elfragmentador/data/predictor.py
elfragmentador/data/torch_datasets.py
elfragmentador/math_utils.py
elfragmentador/metrics.py
elfragmentador/model/__init__.py
elfragmentador/model/ms_transformer_layers.py
elfragmentador/model/nn_encoding.py
elfragmentador/model/peptransformer.py
elfragmentador/model/transformer_layers.py
elfragmentador/model/visualization.py
elfragmentador/named_batches.py
elfragmentador/train.py
elfragmentador/utils.py
elfragmentador/version.py
elfragmentador-0.57.0.dist-info/entry_points.txt
elfragmentador-0.57.0.dist-info/LICENSE
elfragmentador-0.57.0.dist-info/WHEEL
elfragmentador-0.57.0.dist-info/METADATA
elfragmentador-0.57.0.dist-info/RECORD
