Metadata-Version: 2.1
Name: elfragmentador
Version: 0.57.0
Summary: Predicts peptide fragmentations using transformers
License: Apache 2.0
Author: J. Sebastian Paez
Author-email: jspaezp@gmail.com
Requires-Python: >=3.9,<3.11
Classifier: License :: Other/Proprietary License
Classifier: Programming Language :: Python :: 3
Classifier: Programming Language :: Python :: 3.9
Classifier: Programming Language :: Python :: 3.10
Requires-Dist: loguru (>=0.6.0,<0.7.0)
Requires-Dist: lxml (>=4.6.3,<5.0.0)
Requires-Dist: ms2ml (>=0.0.34,<0.1.0)
Requires-Dist: networkx (>=2.8.8,<3.0.0)
Requires-Dist: numba (>=0.56.2,<0.57.0)
Requires-Dist: numpy (>=1.23.2,<2.0.0)
Requires-Dist: pandas (>=1.0.0,<2.0.0)
Requires-Dist: pyarrow (>=9.0.0,<10.0.0)
Requires-Dist: pyteomics (>=4.4.2,<5.0.0)
Requires-Dist: pytorch-lightning (>=1.7.4,<2.0.0)
Requires-Dist: torch (>=1.13.1,<2.0.0)
Requires-Dist: torchmetrics (>=0.9.3,<0.10.0)
Requires-Dist: uniplot (>=0.7.0,<0.8.0)
Requires-Dist: wandb (>=0.13.0,<0.14.0)
Project-URL: Bug Tracker, https://github.com/jspaezp/elfragmentador/issues
